{
  "timestamp": "2025-09-22T10:27:49.375Z",
  "testName": "TS002",
  "error": "\u001b[2mexpect(\u001b[22m\u001b[31mlocator\u001b[39m\u001b[2m).\u001b[22mtoBeVisible\u001b[2m()\u001b[22m failed\n\nLocator:  getByText('Truck Saved Successfully')\nExpected: visible\nReceived: <element(s) not found>\nTimeout:  30000ms\n\nCall log:\n\u001b[2m  - Expect \"toBeVisible\" with timeout 30000ms\u001b[22m\n\u001b[2m  - waiting for getByText('Truck Saved Successfully')\u001b[22m\n",
  "url": "https://mk-bd-dev-uwapp.azurewebsites.net/BD/McKee/index.html?key=fbe5fae8-5ef2-4716-9f7a-627d47ffedee#/Truck",
  "title": "ACME",
  "consoleLogs": [],
  "htmlPath": "C:\\Users\\MohammadRazakAbdulRa\\OneDrive - ValueMomentum, Inc\\Documents\\mcp-playwright\\dom-captures\\TS002_FAILURE_2025-09-22T10-27-48-718Z.html",
  "screenshotPath": "C:\\Users\\MohammadRazakAbdulRa\\OneDrive - ValueMomentum, Inc\\Documents\\mcp-playwright\\dom-captures\\TS002_FAILURE_2025-09-22T10-27-48-718Z.png"
}